odoo/addons/sale_order_invoicing_qty_percentage/README.rst
odoo/addons/sale_order_invoicing_qty_percentage/__init__.py
odoo/addons/sale_order_invoicing_qty_percentage/__manifest__.py
odoo/addons/sale_order_invoicing_qty_percentage/i18n/es.po
odoo/addons/sale_order_invoicing_qty_percentage/i18n/it.po
odoo/addons/sale_order_invoicing_qty_percentage/i18n/sale_order_invoicing_qty_percentage.pot
odoo/addons/sale_order_invoicing_qty_percentage/models/__init__.py
odoo/addons/sale_order_invoicing_qty_percentage/models/sale_order.py
odoo/addons/sale_order_invoicing_qty_percentage/readme/CONTRIBUTORS.md
odoo/addons/sale_order_invoicing_qty_percentage/readme/DESCRIPTION.md
odoo/addons/sale_order_invoicing_qty_percentage/readme/ROADMAP.md
odoo/addons/sale_order_invoicing_qty_percentage/readme/USAGE.md
odoo/addons/sale_order_invoicing_qty_percentage/static/description/icon.png
odoo/addons/sale_order_invoicing_qty_percentage/static/description/index.html
odoo/addons/sale_order_invoicing_qty_percentage/tests/__init__.py
odoo/addons/sale_order_invoicing_qty_percentage/tests/test_sale_order_invoicing_qty_percentage.py
odoo/addons/sale_order_invoicing_qty_percentage/wizards/__init__.py
odoo/addons/sale_order_invoicing_qty_percentage/wizards/sale_advance_payment_inv.py
odoo/addons/sale_order_invoicing_qty_percentage/wizards/sale_advance_payment_inv_views.xml
odoo_addon_sale_order_invoicing_qty_percentage-18.0.1.0.0.2.dist-info/METADATA
odoo_addon_sale_order_invoicing_qty_percentage-18.0.1.0.0.2.dist-info/WHEEL
odoo_addon_sale_order_invoicing_qty_percentage-18.0.1.0.0.2.dist-info/top_level.txt
odoo_addon_sale_order_invoicing_qty_percentage-18.0.1.0.0.2.dist-info/RECORD
